SPyderSQL/__init__.py
SPyderSQL/__meta__.py
SPyderSQL/logger.py
SPyderSQL/my_exception.py
SPyderSQL/py.typed
SPyderSQL/client/AsyncSQLite.py
SPyderSQL/client/SQLRequests.py
SPyderSQL/client/SQLite.py
SPyderSQL/client/__init__.py
SPyderSQL-0.2.0.dist-info/LICENSE
SPyderSQL-0.2.0.dist-info/METADATA
SPyderSQL-0.2.0.dist-info/WHEEL
SPyderSQL-0.2.0.dist-info/top_level.txt
SPyderSQL-0.2.0.dist-info/RECORD
