Metadata-Version: 2.1
Name: SPyderSQL
Version: 0.2.0
Summary: SPyderSQL is a modern ORM framework for SQL database in Python.
Home-page: https://github.com/RealWakeArmilus/SPyderSQL
Author: Emil Artemev
Author-email: jordanman1300@gmail.com
Classifier: Programming Language :: Python :: 3
Classifier: License :: OSI Approved :: MIT License
Classifier: Operating System :: OS Independent
Requires-Python: >=3.6
License-File: LICENSE
Requires-Dist: requests>=2.32.0
Requires-Dist: numpy>=1.19.0
Requires-Dist: pytest>=6.2.5
Requires-Dist: flake8>=3.9.2
Requires-Dist: setuptools~=75.6.0
Requires-Dist: aiosqlite~=0.20.0
